bamdam/__init__.py
bamdam/alignment_utils.py
bamdam/bamdam.py
bamdam/combine.py
bamdam/compute.py
bamdam/extract.py
bamdam/krona.py
bamdam/plotbaminfo.py
bamdam/plotdamage.py
bamdam/shrink.py
bamdam/utils.py
bamdam-0.3.0.dist-info/METADATA
bamdam-0.3.0.dist-info/WHEEL
bamdam-0.3.0.dist-info/entry_points.txt
bamdam-0.3.0.dist-info/licenses/LICENSE
bamdam-0.3.0.dist-info/RECORD
