Metadata-Version: 2.4
Name: bamdam
Version: 0.3.0
Summary: A post-mapping, post-least-common-ancestor toolkit for ancient DNA analysis
Author-email: Bianca De Sanctis <bddesanctis@gmail.com>
License: MIT License
License-File: LICENSE
Requires-Python: >=3.8
Requires-Dist: hyperloglog
Requires-Dist: matplotlib
Requires-Dist: pysam==0.23.0
Requires-Dist: tqdm
